[
    {
        "image": "./images/Breathe Zine BOOK 1.jpg"
    },{
        "image": "./images/Breathe Zine BOOK 2.jpg"
    },{
        "image": "./images/Breathe Zine BOOK 3.jpg"
    },{
        "image": "./images/Breathe Zine BOOK 4.jpg"
    },{
        "image": "./images/Breathe Zine BOOK 5.jpg"
    },{
        "image": "./images/Breathe Zine BOOK 6.jpg"
    },{
        "image": "./images/Breathe Zine BOOK 7.jpg"
    },{
        "image": "./images/Breathe Zine BOOK 8.jpg"
    },{
        "image": "./images/Breathe Zine BOOK 9.jpg"
    },{
        "image": "./images/Breathe Zine BOOK 10.jpg"
    },{
        "image": "./images/Breathe Zine BOOK 11.jpg"
    },{
        "image": "./images/Breathe Zine BOOK 12.jpg"
    },{
        "image": "./images/Breathe Zine BOOK 13.jpg"
    },{
        "image": "./images/Breathe Zine BOOK 14.jpg"
    },{
        "image": "./images/Breathe Zine BOOK 15.jpg"
    },{
        "image": "./images/Breathe Zine BOOK 16.jpg"
    },{
        "image": "./images/Breathe Zine BOOK 17.jpg"
    },{
        "image": "./images/Breathe Zine BOOK 18.jpg"
    },{
        "image": "./images/Breathe Zine BOOK 19.jpg"
    },{
        "image": "./images/Breathe Zine BOOK 20.jpg"
    },{
        "image": "./images/Breathe Zine BOOK 21.jpg"
    },{
        "image": "./images/Breathe Zine BOOK 22.jpg"
    },{
        "image": "./images/Breathe Zine BOOK 23.jpg"
    },{
        "image": "./images/Breathe Zine BOOK 24.jpg"
    },{
        "image": "./images/Breathe Zine BOOK 25.jpg"
    },{
        "image": "./images/Breathe Zine BOOK 26.jpg"
    },{
        "image": "./images/Breathe Zine BOOK 27.jpg"
    },{
        "image": "./images/Breathe Zine BOOK 28.jpg"
    },{
        "image": "./images/Breathe Zine BOOK 29.jpg"
    },{
        "image": "./images/Breathe Zine BOOK 30.jpg"
    },{
        "image": "./images/Breathe Zine BOOK 31.jpg"
    },{
        "image": "./images/Breathe Zine BOOK 32.jpg"
    },{
        "image": "./images/Breathe Zine BOOK 33.jpg"
    },{
        "image": "./images/Breathe Zine BOOK 34.jpg"
    },{
        "image": "./images/Breathe Zine BOOK 35.jpg"
    }
]